{
  "notes": [
    {
      "id": 1,
      "content": "custom-hooks are awesome!"
    },
    {
      "id": 2,
      "content": "best feature ever <3"
    },
    {
      "content": "best team ever",
      "id": 3
    },
    {
      "content": "new test",
      "id": 4
    },
    {
      "id": 5
    },
    {
      "id": 6
    },
    {
      "content": "testing once",
      "id": 7
    },
    {
      "content": "one more note",
      "id": 8
    }
  ],
  "persons": [
    {
      "id": 1,
      "name": "mluukkai",
      "number": "040-5483923"
    },
    {
      "id": 2,
      "name": "hellas",
      "number": "012-123123"
    },
    {
      "name": "Javier",
      "number": "8118001957",
      "id": 3
    },
    {
      "name": "Jorge",
      "number": "66677789",
      "id": 4
    },
    {
      "name": "Divina ",
      "number": "956778961",
      "id": 5
    }
  ]
}